regex_crossword/__init__.py
regex_crossword/crossword.py
regex_crossword/game.py
regex_crossword/level.py
regex_crossword/level_pack.py
regex_crossword/matrix.py
regex_crossword/utils.py
regex_crossword/scripts/__init__.py
regex_crossword/scripts/regex_crossword.py
regex_crossword/scripts/scraper.py
regex_crossword-0.1.0.dist-info/LICENSE
regex_crossword-0.1.0.dist-info/METADATA
regex_crossword-0.1.0.dist-info/WHEEL
regex_crossword-0.1.0.dist-info/entry_points.txt
regex_crossword-0.1.0.dist-info/top_level.txt
regex_crossword-0.1.0.dist-info/RECORD
