Metadata-Version: 2.1
Name: regex-crossword
Version: 0.1.0
Summary: A Python implementation of a Regex Crossword in the terminal.
Home-page: https://github.com/DivoK/regex_crossword
Author: Divo Kaplan
Author-email: divokaplan@gmail.com
License: UNKNOWN
Keywords: terminal curses game regex crossword educational
Platform: UNKNOWN
Classifier: Development Status :: 4 - Beta
Classifier: Environment :: Console :: Curses
Classifier: License :: OSI Approved :: MIT License
Classifier: Operating System :: Unix
Classifier: Programming Language :: Python :: 3.7
Classifier: Programming Language :: Python :: 3.8
Classifier: Intended Audience :: Education
Classifier: Intended Audience :: Other Audience
Classifier: Topic :: Education
Classifier: Topic :: Games/Entertainment :: Puzzle Games
Requires-Python: >=3.7
Provides-Extra: scraper
Requires-Dist: selenium ; extra == 'scraper'
Requires-Dist: beautifulsoup4 ; extra == 'scraper'
Requires-Dist: loguru ; extra == 'scraper'
